opennmt/__init__.py
opennmt/config.py
opennmt/constants.py
opennmt/evaluation.py
opennmt/inference.py
opennmt/runner.py
opennmt/training.py
opennmt/version.py
opennmt/bin/__init__.py
opennmt/bin/ark_to_records.py
opennmt/bin/build_vocab.py
opennmt/bin/detokenize_text.py
opennmt/bin/main.py
opennmt/bin/merge_config.py
opennmt/bin/tokenize_text.py
opennmt/data/__init__.py
opennmt/data/dataset.py
opennmt/data/noise.py
opennmt/data/text.py
opennmt/data/vocab.py
opennmt/decoders/__init__.py
opennmt/decoders/decoder.py
opennmt/decoders/rnn_decoder.py
opennmt/decoders/self_attention_decoder.py
opennmt/encoders/__init__.py
opennmt/encoders/conv_encoder.py
opennmt/encoders/encoder.py
opennmt/encoders/mean_encoder.py
opennmt/encoders/rnn_encoder.py
opennmt/encoders/self_attention_encoder.py
opennmt/inputters/__init__.py
opennmt/inputters/inputter.py
opennmt/inputters/record_inputter.py
opennmt/inputters/text_inputter.py
opennmt/layers/__init__.py
opennmt/layers/bridge.py
opennmt/layers/common.py
opennmt/layers/position.py
opennmt/layers/reducer.py
opennmt/layers/rnn.py
opennmt/layers/transformer.py
opennmt/models/__init__.py
opennmt/models/catalog.py
opennmt/models/language_model.py
opennmt/models/model.py
opennmt/models/sequence_classifier.py
opennmt/models/sequence_tagger.py
opennmt/models/sequence_to_sequence.py
opennmt/models/transformer.py
opennmt/optimizers/__init__.py
opennmt/optimizers/utils.py
opennmt/schedules/__init__.py
opennmt/schedules/lr_schedules.py
opennmt/tokenizers/__init__.py
opennmt/tokenizers/opennmt_tokenizer.py
opennmt/tokenizers/sentencepiece_tokenizer.py
opennmt/tokenizers/tokenizer.py
opennmt/utils/__init__.py
opennmt/utils/checkpoint.py
opennmt/utils/compat.py
opennmt/utils/decoding.py
opennmt/utils/exporters.py
opennmt/utils/fmeasure.py
opennmt/utils/losses.py
opennmt/utils/misc.py
opennmt/utils/scorers.py
opennmt/utils/tensor.py
opennmt/utils/wer.py
OpenNMT_tf-2.32.0.dist-info/LICENSE
OpenNMT_tf-2.32.0.dist-info/METADATA
OpenNMT_tf-2.32.0.dist-info/WHEEL
OpenNMT_tf-2.32.0.dist-info/entry_points.txt
OpenNMT_tf-2.32.0.dist-info/top_level.txt
OpenNMT_tf-2.32.0.dist-info/RECORD
