Metadata-Version: 2.1
Name: OpenNMT-tf
Version: 2.32.0
Summary: Neural machine translation and sequence learning using TensorFlow
Home-page: https://opennmt.net
Author: OpenNMT
License: MIT
Project-URL: Documentation, https://opennmt.net/OpenNMT-tf/
Project-URL: Forum, https://forum.opennmt.net/
Project-URL: Gitter, https://gitter.im/OpenNMT/OpenNMT-tf
Project-URL: Source, https://github.com/OpenNMT/OpenNMT-tf/
Keywords: tensorflow opennmt nmt neural machine translation
Platform: UNKNOWN
Classifier: Development Status :: 5 - Production/Stable
Classifier: Intended Audience :: Developers
Classifier: Intended Audience :: Science/Research
Classifier: License :: OSI Approved :: MIT License
Classifier: Programming Language :: Python :: 3
Classifier: Programming Language :: Python :: 3 :: Only
Classifier: Programming Language :: Python :: 3.7
Classifier: Programming Language :: Python :: 3.8
Classifier: Programming Language :: Python :: 3.9
Classifier: Programming Language :: Python :: 3.10
Classifier: Programming Language :: Python :: 3.11
Classifier: Topic :: Scientific/Engineering :: Artificial Intelligence
Requires-Python: >=3.7
Requires-Dist: ctranslate2 (<4,>=3.0)
Requires-Dist: packaging
Requires-Dist: pyonmttok (<2,>=1.29.0)
Requires-Dist: pyyaml (<7,>=5.3)
Requires-Dist: rouge (<2,>=1.0)
Requires-Dist: sacrebleu (<3,>=1.5.0)
Requires-Dist: tensorflow-addons (<0.22,>=0.16)
Provides-Extra: docs
Requires-Dist: myst-parser (==0.17.*) ; extra == 'docs'
Requires-Dist: sphinx-rtd-theme (==1.0.*) ; extra == 'docs'
Requires-Dist: sphinx (==4.5.*) ; extra == 'docs'
Provides-Extra: tensorflow
Requires-Dist: tensorflow (<2.14.0,>=2.6.0) ; extra == 'tensorflow'
Requires-Dist: tensorflow-text (<2.14.0,>=2.6.0) ; extra == 'tensorflow'
Provides-Extra: tests
Requires-Dist: black (==22.*) ; extra == 'tests'
Requires-Dist: flake8 (==3.9.*) ; extra == 'tests'
Requires-Dist: isort (<6,>=5.9) ; extra == 'tests'
Requires-Dist: parameterized (==0.8.1) ; extra == 'tests'
Requires-Dist: pytest-cov ; extra == 'tests'
